hybrid_vectorizer/__init__.py
hybrid_vectorizer/core.py
hybrid_vectorizer/exceptions.py
hybrid_vectorizer-0.1.2.dist-info/licenses/LICENSE.txt
hybrid_vectorizer-0.1.2.dist-info/METADATA
hybrid_vectorizer-0.1.2.dist-info/WHEEL
hybrid_vectorizer-0.1.2.dist-info/top_level.txt
hybrid_vectorizer-0.1.2.dist-info/RECORD
