Metadata-Version: 2.4
Name: hybrid-vectorizer
Version: 0.1.2
Summary: Unified embedding for tabular, text, and multimodal data
Author-email: Hari Narayanan <hari.dataprojects@gmail.com>
License: Apache-2.0
Project-URL: Homepage, https://github.com/hariharaprabhu/hybrid-vectorizer
Project-URL: Repository, https://github.com/hariharaprabhu/hybrid-vectorizer
Project-URL: Issues, https://github.com/hariharaprabhu/hybrid-vectorizer/issues
Project-URL: Example Notebooks, https://github.com/hariharaprabhu/hybrid-vectorizer/tree/Examples
Project-URL: Documentation, https://github.com/hariharaprabhu/hybrid-vectorizer#readme
Keywords: machine-learning,embeddings,similarity-search,multimodal,vectorization
Classifier: Development Status :: 4 - Beta
Classifier: Intended Audience :: Developers
Classifier: License :: OSI Approved :: Apache Software License
Classifier: Operating System :: OS Independent
Classifier: Programming Language :: Python :: 3
Classifier: Programming Language :: Python :: 3.8
Classifier: Programming Language :: Python :: 3.9
Classifier: Programming Language :: Python :: 3.10
Classifier: Programming Language :: Python :: 3.11
Classifier: Programming Language :: Python :: 3.12
Classifier: Topic :: Scientific/Engineering :: Artificial Intelligence
Classifier: Topic :: Software Development :: Libraries :: Python Modules
Requires-Python: >=3.8
License-File: LICENSE.txt
Requires-Dist: numpy>=1.26; python_version >= "3.12"
Requires-Dist: numpy<2.0,>=1.21; python_version < "3.12"
Requires-Dist: pandas>=1.3.0
Requires-Dist: scikit-learn>=1.0.0
Requires-Dist: sentence-transformers>=2.0.0
Requires-Dist: joblib>=1.0.0
Provides-Extra: dev
Requires-Dist: pytest>=6.0; extra == "dev"
Requires-Dist: black>=21.0; extra == "dev"
Requires-Dist: flake8>=3.8; extra == "dev"
Provides-Extra: test
Requires-Dist: pytest>=6.0; extra == "test"
Provides-Extra: faiss
Requires-Dist: faiss-cpu>=1.7.0; extra == "faiss"
Provides-Extra: gpu
Requires-Dist: torch>=1.9.0; extra == "gpu"
Dynamic: license-file
